overlord/__init__.py
overlord/app.py
overlord/install_dependencies.py
overlord/loop.py
overlord/tools/__init__.py
overlord/tools/base.py
overlord/tools/bash.py
overlord/tools/collection.py
overlord/tools/computer.py
overlord/tools/edit.py
overlord/tools/run.py
hanzo_overlord-0.1.0.dist-info/METADATA
hanzo_overlord-0.1.0.dist-info/WHEEL
hanzo_overlord-0.1.0.dist-info/entry_points.txt
hanzo_overlord-0.1.0.dist-info/top_level.txt
hanzo_overlord-0.1.0.dist-info/RECORD
