Metadata-Version: 2.4
Name: hanzo-overlord
Version: 0.1.0
Summary: Mac automation and streamlit interface tools
Author: Hanzo Team
License-Expression: MIT
Requires-Python: >=3.13
Requires-Dist: streamlit>=1.43.0
Requires-Dist: anthropic[bedrock,vertex]>=0.37.1
Requires-Dist: jsonschema>=4.0.0
Requires-Dist: keyboard>=0.13.5
Requires-Dist: boto3>=1.28.57
Requires-Dist: google-auth>=2.0.0
Requires-Dist: python-dotenv>=1.0.1
Requires-Dist: watchdog>=5.0.3
Requires-Dist: mouse>=0.7.1
Requires-Dist: pynput>=1.7.6
Provides-Extra: dev
Requires-Dist: pytest>=7.0.0; extra == "dev"
Requires-Dist: ruff>=0.1.0; extra == "dev"
Requires-Dist: black>=23.0.0; extra == "dev"
Requires-Dist: mypy>=1.0.0; extra == "dev"
